kyqacommon/__init__.py
kyqacommon/getLogger.py
kyqacommon/minio_handld.py
kyqacommon/uiCommonMethod.py
kyqacommon/tools/__init__.py
kyqacommon/tools/cpu_ssh.py
kyqacommon/tools/dataBase.py
kyqacommon/tools/loading_ly.py
kyqacommon-1.0.908.dist-info/LICENSE
kyqacommon-1.0.908.dist-info/METADATA
kyqacommon-1.0.908.dist-info/WHEEL
kyqacommon-1.0.908.dist-info/top_level.txt
kyqacommon-1.0.908.dist-info/RECORD
